{
  "ip": "2.56.165.46",
  "owner_discord_id": "828235961837813760",
  "owner_name": "o32i",
  "server_name": "مدينة الوادي",
  "owners": [
    {
      "discord_id": "828235961837813760",
      "username": "o32i",
      "server_name": "مدينة الوادي"
    }
  ],
  "resources": [
    {
      "product_id": 26,
      "name": "YB_GangSystem",
      "type": "system",
      "version": "3.0.1",
      "enforce_version": false,
      "expires_at": null
    },
    {
      "product_id": 22,
      "name": "YB_OwnedMechanic | تملك الورش",
      "type": "system",
      "version": "1.0.0",
      "enforce_version": false,
      "expires_at": null
    },
    {
      "product_id": 16,
      "name": "YB_RobberySystem",
      "type": "system",
      "version": "1.0.0",
      "enforce_version": true,
      "expires_at": null
    }
  ],
  "updated_at": "2026-07-03T05:42:15.569Z"
}